finq/__init__.py
finq/__version__.py
finq/asset.py
finq/datasets/__init__.py
finq/datasets/custom.py
finq/datasets/dataset.py
finq/datasets/ndx.py
finq/datasets/omxs30.py
finq/datasets/omxsbesgni.py
finq/datasets/omxspi.py
finq/datasets/snp500.py
finq/datautil/__init__.py
finq/datautil/cached_rate_limiter.py
finq/datautil/nasdaq_utils.py
finq/datautil/path_utils.py
finq/exceptions.py
finq/formulas.py
finq/log.py
finq/portfolio.py
pyfinq-0.4.0.dist-info/LICENSE
pyfinq-0.4.0.dist-info/METADATA
pyfinq-0.4.0.dist-info/WHEEL
pyfinq-0.4.0.dist-info/RECORD
