Metadata-Version: 2.1
Name: pyfinq
Version: 0.4.0
Summary: 🔬 Quantitative analysis and management for financial applications. 
Home-page: https://github.com/wilhelmagren/finq
License: MIT
Keywords: finance,nasdaq,investment,yahoo-finance,data-science,time-series,analysis,optimization,data-analysis,quantiative-finance,portfolio-optimization,portfolio-management
Author: Wilhelm Ågren
Author-email: wilhelmagren98@gmail.com
Requires-Python: >=3.9,<3.13
Classifier: Intended Audience :: Developers
Classifier: License :: OSI Approved :: MIT License
Classifier: Operating System :: OS Independent
Classifier: Programming Language :: Python :: 3
Classifier: Programming Language :: Python :: 3.9
Classifier: Programming Language :: Python :: 3.10
Classifier: Programming Language :: Python :: 3.11
Classifier: Programming Language :: Python :: 3.12
Requires-Dist: matplotlib (>=3.8.0,<4.0.0)
Requires-Dist: mplfinance (>=0.12.10b0,<0.13.0)
Requires-Dist: numpy (>=1.26.0,<2.0.0)
Requires-Dist: openpyxl (>=3.1.2,<4.0.0)
Requires-Dist: pandas (>=2.1.1,<3.0.0)
Requires-Dist: pyrate-limiter (>=2.8.0,<3.0.0)
Requires-Dist: requests (>=2.31.0,<3.0.0)
Requires-Dist: requests-cache (>=1.1.0,<2.0.0)
Requires-Dist: requests-ratelimiter (==0.4.2)
Requires-Dist: scipy (>=1.11.3,<2.0.0)
Requires-Dist: tqdm (>=4.66.1,<5.0.0)
Requires-Dist: yfinance (>=0.2.31,<0.3.0)
Project-URL: Bug tracker, https://github.com/wilhelmagren/finq/issues
Project-URL: Repository, https://github.com/wilhelmagren/finq
